vending/fsm.v
module fsm(in,rst,out,clk);
    input [1:0]in;
    input rst;
    output out;
    input clk;
    reg out;

    reg [2:0]state;

    parameter s0 = 3'b000,
              s1 = 3'b001,
              s2 = 3'b010,
              s3 = 3'b100,
              s4 = 3'b101,
              rs1=2'b01,
              rs2=2'b10,
              rs5=2'b11;

    always @(negedge clk)
    begin
        if (rst==1)
            begin
            case (state)
                s0 : begin
                    if (in==rs1) begin
                        state=s1; 
                        out=0;
                    end
                    else if(in==rs2) begin
                        state=s2; 
                        out=0;
                        end
                    else if(in==rs5) begin
                        state=s0; 
                        out=1;
                        end
                    else begin
                        state=s0; 
                        out=0;
                        end
                end 

                s1 : begin
                    if (in==rs1) begin
                        state=s2; 
                        out=0;
                        end
                    else if(in==rs2) begin
                        state=s3; 
                        out=0;
                        end
                    else if(in==rs5) begin
                        state=s1; 
                        out=1;
                        end
                    else begin
                        state=s0; 
                        out=0;
                        end
                end 

                s2 : begin
                    if (in==rs1) begin
                        state=s3; 
                        out=0;
                        end
                    else if(in==rs2) begin
                        state=s4; 
                        out=0;
                        end
                    else if(in==rs5) begin
                        state=s2; 
                        out=1;
                        end
                    else begin
                        state=s0; 
                        out=0;
                        end
                end 

                s3 : begin
                    if (in==rs1) begin
                        state=s4; 
                        out=0;
                        end
                    else if(in==rs2) begin
                        state=s0; 
                        out=1;
                        end
                    else if(in==rs5) begin
                        state=s3; 
                        out=1;
                        end
                    else begin
                        state=s0; 
                        out=0;
                        end
                end 

                s4 : begin
                    if (in==rs1) begin
                        state=s0; 
                        out=1;
                        end
                    else if(in==rs2) begin
                        state=s1; 
                        out=1;
                        end
                    else if(in==rs5) begin
                        state=s4; 
                        out=1;
                        end
                    else begin
                        state=s0; 
                        out=0;
                        end
                end 
                default: state=s0;
            endcase
        end
        
        else
        begin
            out=0;
            state=s0;
        end
        
    end
endmodule

vending/fsm_tb.v
`timescale 1ns/1ns
module fsm_tb ();
    
    reg rst;
    reg [1:0]in;
    wire out;
    reg clk;
    parameter rs1=2'b01,
              rs2=2'b10,
              rs5=2'b11,
              rs0=2'b00;

    fsm uut(in,rst,out,clk);


    initial begin
        rst=1;
        in=2'b00;
        clk=0;
        forever begin
            #3 clk=~clk;
        end
    end

    initial
    begin
        $dumpfile("wave.vcd");
        $dumpvars(0,fsm_tb);
        #1  in=rs0;
        #5 in=rs1;
        #5 in=rs1;
        #5 in=rs2;
        #5 in=rs2;
        #5 in=rs0;
        #5 in=rs0;
        #5 in=rs5;
        #5 in=rs1;
        #5 in=rs0;
        #5 in=rs2;
        #5 in=rs5;
        #5 in=rs0;
        #5 in=rs1;
        #5 in=rs1;
        #5 in=rs1;
        #5 in=rs0;
        #5 in=rs1;
        #5 $finish;
        
    end
    
endmodule

vending/wave.vcd
$date
	Sun Jan 22 17:12:31 2023
$end
$version
	Icarus Verilog
$end
$timescale
	1ns
$end
$scope module fsm_tb $end
$var wire 1 ! out $end
$var reg 1 " clk $end
$var reg 2 # in [1:0] $end
$var reg 1 $ rst $end
$scope module uut $end
$var wire 1 " clk $end
$var wire 2 % in [1:0] $end
$var wire 1 $ rst $end
$var reg 1 ! out $end
$var reg 3 & state [2:0] $end
$upscope $end
$upscope $end
$enddefinitions $end
#0
$dumpvars
b0 &
b0 %
1$
b0 #
0"
x!
$end
#3
1"
#6
0!
b1 &
0"
b1 #
b1 %
#9
1"
#12
b10 &
0"
#15
1"
#16
b10 #
b10 %
#18
b101 &
0"
#21
1"
#24
1!
b1 &
0"
#26
b0 #
b0 %
#27
1"
#30
0!
b0 &
0"
#33
1"
#36
1!
0"
b11 #
b11 %
#39
1"
#41
b1 #
b1 %
#42
0!
b1 &
0"
#45
1"
#46
b0 #
b0 %
#48
b0 &
0"
#51
1"
b10 #
b10 %
#54
b10 &
0"
#56
b11 #
b11 %
#57
1"
#60
1!
0"
#61
b0 #
b0 %
#63
1"
#66
0!
b100 &
0"
b1 #
b1 %
#69
1"
#72
b101 &
0"
#75
1"
#78
1!
b0 &
0"
#81
1"
b0 #
b0 %
#84
0!
0"
#86
b1 #
b1 %
#87
1"
#90
b1 &
0"
